CITATION.cff
COPYING
MANIFEST.in
README.md
pyproject.toml
setup.py
chamois/__init__.py
chamois/_json.py
chamois/_meta.py
chamois/classyfire.py
chamois/compositions.py
chamois/model.py
chamois/ontology.py
chamois/orf.py
chamois/cli/__init__.py
chamois/cli/__main__.py
chamois/cli/_common.py
chamois/cli/_parser.py
chamois/cli/_utils.py
chamois/cli/annotate.py
chamois/cli/compare.py
chamois/cli/cv.py
chamois/cli/cvi.py
chamois/cli/cvsearch.py
chamois/cli/explain.py
chamois/cli/predict.py
chamois/cli/render.py
chamois/cli/search.py
chamois/cli/train.py
chamois/cli/validate.py
chamois/domains/__init__.py
chamois/predictor/__init__.py
chamois/predictor/information.py
chamois/predictor/predictor.json
chamois_tool.egg-info/PKG-INFO
chamois_tool.egg-info/SOURCES.txt
chamois_tool.egg-info/dependency_links.txt
chamois_tool.egg-info/entry_points.txt
chamois_tool.egg-info/requires.txt
chamois_tool.egg-info/top_level.txt
tests/test_domains.py
tests/test_orf.py
tests/test_predictor.py