Metadata-Version: 2.4
Name: chamois-tool
Version: 0.2.1
Summary: Chemical HierArchy for Metabolites Obtained In Silico.
Author-email: Martin Larralde <martin.larralde@embl.de>
License-Expression: GPL-3.0-or-later
Project-URL: Repository, https://github.com/zellerlab/CHAMOIS
Project-URL: Bug Tracker, https://github.com/zellerlab/CHAMOIS/issues
Project-URL: Changelog, https://github.com/zellerlab/CHAMOIS/blob/main/CHANGELOG.md
Project-URL: Preprint, https://www.biorxiv.org/content/10.1101/2025.03.13.642868
Keywords: bioinformatics,metabolism,gene cluster,bgc
Classifier: Development Status :: 4 - Beta
Classifier: Intended Audience :: Science/Research
Classifier: Operating System :: POSIX
Classifier: Programming Language :: Python :: 3 :: Only
Classifier: Topic :: Scientific/Engineering :: Bio-Informatics
Classifier: Typing :: Typed
Requires-Python: >=3.7
License-File: COPYING
Requires-Dist: anndata<0.13,>=0.8
Requires-Dist: gb-io~=0.3.1
Requires-Dist: importlib-resources>=1.0; python_version < "3.9"
Requires-Dist: lz4~=4.0
Requires-Dist: numpy<3.0,>=1.0
Requires-Dist: pandas<3.0,>=1.3
Requires-Dist: platformdirs<5.0,>=3.0
Requires-Dist: pyhmmer~=0.12.0
Requires-Dist: pyrodigal~=3.0
Requires-Dist: rich>=12.4.0
Requires-Dist: rich-argparse~=1.1
Requires-Dist: scipy~=1.4
Provides-Extra: train
Requires-Dist: scikit-learn~=1.0; extra == "train"
Requires-Dist: kennard-stone~=2.1; extra == "train"
Provides-Extra: compare
Requires-Dist: rdkit>=2023.3; extra == "compare"
Dynamic: license-file
